assets/img.png
assets/img_1.png
nanocode38_pyhelper-2.7.0.dist-info/licenses/AUTHORS.md
nanocode38_pyhelper-2.7.0.dist-info/licenses/LICENSE
pyhelper/__init__.py
pyhelper/color.py
pyhelper/mathhelper.py
pyhelper/namespace.py
pyhelper/random.py
pyhelper/tkhelper.py
pyhelper/gamehelpers/__init__.py
pyhelper/gamehelpers/pghelper/__init__.py
pyhelper/gamehelpers/pghelper/widgets.py
tests/__init__.py
tests/test_all.py
tests/__pycache__/tests_wheel/test.py
nanocode38_pyhelper-2.7.0.dist-info/METADATA
nanocode38_pyhelper-2.7.0.dist-info/WHEEL
nanocode38_pyhelper-2.7.0.dist-info/top_level.txt
nanocode38_pyhelper-2.7.0.dist-info/RECORD
