Metadata-Version: 2.4
Name: nanocode38-pyhelper
Version: 2.7.0
Summary: A tool set for complementing Python and Pygame
Author-email: nanocode38 <nanocode38@88.com>
License: MIT License
Project-URL: repository, https://github.com/nanocode38/pyhelper.git
Classifier: Intended Audience :: Developers
Classifier: Operating System :: OS Independent
Classifier: Natural Language :: Chinese (Simplified)
Classifier: Programming Language :: Python :: 3
Classifier: Programming Language :: Python :: 3.9
Classifier: Programming Language :: Python :: 3.10
Classifier: Programming Language :: Python :: 3.11
Classifier: Programming Language :: Python :: 3.12
Classifier: Programming Language :: Python :: 3.13
Classifier: Topic :: Software Development :: Libraries
Requires-Python: >=3.13
License-File: LICENSE
License-File: AUTHORS.md
Requires-Dist: pygame
Requires-Dist: numba
Requires-Dist: pywin32>=311
Provides-Extra: dev
Requires-Dist: black; extra == "dev"
Requires-Dist: autoflake; extra == "dev"
Requires-Dist: isort; extra == "dev"
Requires-Dist: setuptools; extra == "dev"
Requires-Dist: wheel; extra == "dev"
Dynamic: license-file
